Metadata-Version: 2.1
Name: tiktokscraper
Version: 0.1.0
Summary: A simple webscraper for tiktok data
Home-page: https://github.com/westonbattles/tiktok-webscraper
Author: Weston Battles
Author-email: westonb.work@gmail.com
License: MIT
Platform: UNKNOWN
Classifier: Development Status :: 3 - Alpha
Classifier: Intended Audience :: Developers
Classifier: License :: OSI Approved :: MIT License
Classifier: Operating System :: OS Independent
Classifier: Programming Language :: Python :: 3
